README.rst
setup.py
us_polygon_mapper/__init__.py
us_polygon_mapper/color_rgb_dict.py
us_polygon_mapper/defaults.py
us_polygon_mapper/state_polygon_dict.pickle
us_polygon_mapper/us_polygon_mapper.py
us_polygon_mapper/us_state_abbrev.py
us_polygon_mapper.egg-info/PKG-INFO
us_polygon_mapper.egg-info/SOURCES.txt
us_polygon_mapper.egg-info/dependency_links.txt
us_polygon_mapper.egg-info/requires.txt
us_polygon_mapper.egg-info/top_level.txt