Metadata-Version: 1.0
Name: us-polygon-mapper
Version: 1.0.0
Summary: Create Google Maps US polygon maps from csv's, python dictionaries and pandas dataframes
Home-page: https://github.com/abulow/us_polygon_mapper
Author: Adam Bulow
Author-email: adamjbulow@gmail.com
License: LICENSE.txt
Platform: UNKNOWN
